aiorocket/__init__.py
aiorocket/classes.py
aiorocket-1.3.1.dist-info/LICENSE.txt
aiorocket-1.3.1.dist-info/METADATA
aiorocket-1.3.1.dist-info/WHEEL
aiorocket-1.3.1.dist-info/top_level.txt
aiorocket-1.3.1.dist-info/RECORD
