Metadata-Version: 2.1
Name: aiorocket
Version: 1.3.1
Summary: Async Python SDK for TON Rocket
Author-email: Sovenok-Hacker <artemka.hvostov@yandex.ru>
Project-URL: homepage, https://github.com/Sovenok-Hacker/aiorocket
Project-URL: repository, https://github.com/Sovenok-Hacker/aiorocket.git
Project-URL: MainnetBot, https://t.me/tonRocketBot
Project-URL: TestnetBot, https://t.me/ton_rocket_test_bot
Project-URL: Creator, https://t.me/Duo_sova
Keywords: ton,rocket,sdk,async,the open network,bot,telegram,crypto,cryptocurrency
Classifier: Development Status :: 4 - Beta
Classifier: Programming Language :: Python
Requires-Python: >=3.7
License-File: LICENSE.txt
Requires-Dist: aiohttp
